sphinx_search/__init__.py
sphinx_search/extension.py
sphinx_search/static/css/rtd_sphinx_search.css
sphinx_search/static/css/rtd_sphinx_search.min.css
sphinx_search/static/js/rtd_search_config.js_t
sphinx_search/static/js/rtd_sphinx_search.js
sphinx_search/static/js/rtd_sphinx_search.min.js
readthedocs_sphinx_search-0.3.2.dist-info/LICENSE
readthedocs_sphinx_search-0.3.2.dist-info/METADATA
readthedocs_sphinx_search-0.3.2.dist-info/WHEEL
readthedocs_sphinx_search-0.3.2.dist-info/top_level.txt
readthedocs_sphinx_search-0.3.2.dist-info/RECORD
