Metadata-Version: 2.1
Name: readthedocs-sphinx-search
Version: 0.3.2
Summary: Sphinx extension to enable search as you type for docs hosted on Read the Docs.
Home-page: https://github.com/readthedocs/readthedocs-sphinx-search
Author: Vaibhav Gupta
Author-email: vaibhgupt199@gmail.com
License: MIT
Project-URL: Documentation, https://readthedocs-sphinx-search.readthedocs.io/
Project-URL: Bug Reports, https://github.com/readthedocs/readthedocs-sphinx-search/issues
Project-URL: Source, https://github.com/readthedocs/readthedocs-sphinx-search
Keywords: sphinx search readthedocs
Classifier: Development Status :: 4 - Beta
Classifier: Programming Language :: Python :: 3
Classifier: License :: OSI Approved :: MIT License
Classifier: Operating System :: OS Independent
Classifier: Framework :: Sphinx :: Extension
Requires-Python: >=3.6
License-File: LICENSE
